openpibo_models/__init__.py
openpibo_models/models/KDL.ttf
openpibo_models/models/NS_CJK_R.otf
openpibo_models/models/dialog.csv
openpibo_models/models/dialog_en.csv
openpibo_models/models/motion_db.json
openpibo_models/models/pibo_graphic.png
openpibo_models/models/sample_db.json
openpibo_models-0.4.9.dist-info/METADATA
openpibo_models-0.4.9.dist-info/WHEEL
openpibo_models-0.4.9.dist-info/top_level.txt
openpibo_models-0.4.9.dist-info/RECORD
