Metadata-Version: 2.1
Name: openpibo-models
Version: 0.4.9
Summary: Models used by the openpibo-python package.
Home-page: https://github.com/themakerrobot/openpibo_models
Author: circulus
Author-email: leeyunjai@circul.us
Keywords: openpibo
Classifier: Natural Language :: English
Classifier: Programming Language :: Python :: 3.5
Classifier: Programming Language :: Python :: 3.6
Classifier: Programming Language :: Python :: 3.7
Classifier: Programming Language :: Python :: 3.8
Classifier: Programming Language :: Python :: 3.9
Classifier: Programming Language :: Python :: 3.10
Classifier: Programming Language :: Python :: 3.11
Classifier: Programming Language :: Python :: 3.12
